gridsim/__init__.py
gridsim/config_parser.py
gridsim/environment.py
gridsim/grid_robot.py
gridsim/logger.py
gridsim/message.py
gridsim/robot.py
gridsim/utils.py
gridsim/viewer.py
gridsim/world.py
gridsim-0.4.dist-info/LICENSE
gridsim-0.4.dist-info/METADATA
gridsim-0.4.dist-info/WHEEL
gridsim-0.4.dist-info/top_level.txt
gridsim-0.4.dist-info/RECORD
