Metadata-Version: 2.1
Name: gridsim
Version: 0.4
Summary: Simple grid-based robot simulator
Home-page: https://gridsim.readthedocs.io
Author: Julia Ebert
Author-email: julia@juliaebert.com
License: UNKNOWN
Download-URL: https://github.com/jtebert/gridsim
Platform: UNKNOWN
Classifier: Programming Language :: Python :: 3
Classifier: License :: OSI Approved :: MIT License
Classifier: Framework :: Robot Framework
Classifier: Development Status :: 3 - Alpha
Requires-Python: >=3.6
Requires-Dist: pygame
Requires-Dist: numpy
Requires-Dist: h5py
Requires-Dist: pyyaml
Requires-Dist: pillow
